bvg_grabber-0.2.1.data/scripts/bvg-grabber.py
bvggrabber/__init__.py
bvggrabber/api/__init__.py
bvggrabber/api/actualdeparture.py
bvggrabber/api/scheduleddeparture.py
bvggrabber/utils/__init__.py
bvggrabber/utils/format.py
bvggrabber/utils/json.py
bvg_grabber-0.2.1.dist-info/AUTHORS
bvg_grabber-0.2.1.dist-info/LICENSE
bvg_grabber-0.2.1.dist-info/METADATA
bvg_grabber-0.2.1.dist-info/WHEEL
bvg_grabber-0.2.1.dist-info/top_level.txt
bvg_grabber-0.2.1.dist-info/RECORD
