Metadata-Version: 2.1
Name: bvg-grabber
Version: 0.2.1
Summary: Querying the upcoming public transport departures in Berlin
Home-page: https://github.com/MarkusH/bvg-grabber
Author: Christian Struck, Markus Holtermann
Author-email: info@markusholtermann.eu
License: BSD
Platform: UNKNOWN
Classifier: Development Status :: 4 - Beta
Classifier: Environment :: Console
Classifier: Intended Audience :: Developers
Classifier: License :: OSI Approved :: BSD License
Classifier: Operating System :: OS Independent
Classifier: Programming Language :: Python :: 3.4
Classifier: Programming Language :: Python :: 3.6
Classifier: Programming Language :: Python :: 3.7
Classifier: Programming Language :: Python :: 3.8
License-File: LICENSE
License-File: AUTHORS
Requires-Dist: beautifulsoup4 (>=4.4.1)
Requires-Dist: python-dateutil (>=2.1)
Requires-Dist: requests (>=1.2.3)
Requires-Dist: six (>=1.3.0)
